viramp_hub/__init__.py
viramp_hub/command.py
viramp_hub/scheme.py
viramp_hub-0.1.0.dist-info/LICENSE
viramp_hub-0.1.0.dist-info/METADATA
viramp_hub-0.1.0.dist-info/WHEEL
viramp_hub-0.1.0.dist-info/entry_points.txt
viramp_hub-0.1.0.dist-info/top_level.txt
viramp_hub-0.1.0.dist-info/RECORD
