Metadata-Version: 2.1
Name: viramp-hub
Version: 0.1.0
Summary: VirAmp-Hub lets you manipulate/convert viral amplicon/primer scheme information.
Author-email: Wolfgang Maier <maierw@informatik.uni-freiburg.de>
License: MIT License
Project-URL: Homepage, https://github.com/wm75/viramp-hub
Keywords: virology,tiled-amplicon,primer schemes
Classifier: License :: OSI Approved :: MIT License
Classifier: Programming Language :: Python :: 3
Classifier: Development Status :: 4 - Beta
Classifier: Operating System :: OS Independent
Classifier: Topic :: Scientific/Engineering
Classifier: Topic :: Scientific/Engineering :: Bio-Informatics
Classifier: Intended Audience :: Science/Research
Classifier: Natural Language :: English
Requires-Python: >=3.6
License-File: LICENSE
